datek_agar_kivy/__init__.py
datek_agar_kivy/agar.kv
datek_agar_kivy/agar.py
datek_agar_kivy/utils.py
datek_agar_kivy-0.1.2.dist-info/entry_points.txt
datek_agar_kivy-0.1.2.dist-info/LICENSE
datek_agar_kivy-0.1.2.dist-info/WHEEL
datek_agar_kivy-0.1.2.dist-info/METADATA
datek_agar_kivy-0.1.2.dist-info/RECORD
