Metadata-Version: 2.1
Name: datek-agar-kivy
Version: 0.1.2
Summary: Kivy client for Agar game
Home-page: https://github.com/DAtek/datek-agar-kivy
License: MIT
Author: Attila Dudas
Author-email: dudasa7@gmail.com
Requires-Python: >=3.9,<4.0
Classifier: License :: OSI Approved :: MIT License
Classifier: Programming Language :: Python :: 3
Classifier: Programming Language :: Python :: 3.10
Classifier: Programming Language :: Python :: 3.9
Requires-Dist: Kivy (>=2.1.0dev0,<3.0.0)
Requires-Dist: datek-agar-core (>=0.1.0,<0.2.0)
Requires-Dist: numpy (>=1.20.0,<2.0.0)
Project-URL: Repository, https://github.com/DAtek/datek-agar-kivy
